{
  "packages": {
    ".": {
      "initial-version": "0.1.0",
      "include-v-in-tag": true,
      "include-component-in-tag": false,
      "release-type": "go",
      "prerelease": false,
      "draft": false,
      "bump-minor-pre-major": true,
      "bump-patch-for-minor-pre-major": false,
      "bootstrap-sha": "5efee077429453c76772f379666241b38fbba7ad",
      "extra-files": ["examples/who-am-i/docker-compose.yaml"],
      "changelog-sections": [
        {
          "type": "feat",
          "section": "Features"
        },
        {
          "type": "fix",
          "section": "Bug Fixes"
        },
        {
          "type": "chore",
          "section": "Other"
        },
        {
          "type": "docs",
          "section": "Docs"
        },
        {
          "type": "perf",
          "section": "Performance"
        },
        {
          "type": "build",
          "hidden": true,
          "section": "Build"
        },
        {
          "type": "deps",
          "section": "Dependency Updates"
        },
        {
          "type": "ci",
          "hidden": true,
          "section": "CI"
        },
        {
          "type": "refactor",
          "section": "Refactoring"
        },
        {
          "type": "revert",
          "hidden": true,
          "section": "Reverts"
        },
        {
          "type": "style",
          "hidden": true,
          "section": "Styling"
        },
        {
          "type": "test",
          "hidden": true,
          "section": "Tests"
        }
      ]
    }
  },
  "$schema": "https://raw.githubusercontent.com/googleapis/release-please/main/schemas/config.json"
}
